MANIFEST.in
README.md
setup.py
docs/man/labelme.1
labelme/__init__.py
labelme/__main__.py
labelme/app.py
labelme/label_file.py
labelme/logger.py
labelme/shape.py
labelme/testing.py
labelme/cli/__init__.py
labelme/cli/draw_json.py
labelme/cli/draw_label_png.py
labelme/cli/json_to_dataset.py
labelme/cli/on_docker.py
labelme/config/__init__.py
labelme/config/default_config.yaml
labelme/icons/annotate.png
labelme/icons/automate.png
labelme/icons/cancel.png
labelme/icons/close.png
labelme/icons/color-line.png
labelme/icons/color.png
labelme/icons/copy.png
labelme/icons/delete.png
labelme/icons/done.png
labelme/icons/done.svg
labelme/icons/edit.png
labelme/icons/expert.png
labelme/icons/eye.png
labelme/icons/feBlend-icon.png
labelme/icons/file.png
labelme/icons/fit-width.png
labelme/icons/fit-window.png
labelme/icons/fit.png
labelme/icons/help.png
labelme/icons/icon.icns
labelme/icons/icon.ico
labelme/icons/icon.png
labelme/icons/labels.png
labelme/icons/labels.svg
labelme/icons/new.png
labelme/icons/next.png
labelme/icons/objects.png
labelme/icons/open.png
labelme/icons/open.svg
labelme/icons/prev.png
labelme/icons/quit.png
labelme/icons/save-as.png
labelme/icons/save-as.svg
labelme/icons/save.png
labelme/icons/save.svg
labelme/icons/server.png
labelme/icons/undo-cross.png
labelme/icons/undo.png
labelme/icons/zoom-in.png
labelme/icons/zoom-out.png
labelme/icons/zoom.png
labelme/products/fairy.jpg
labelme/products/gillette.jpg
labelme/products/h&s.jpg
labelme/products/missing_file.png
labelme/products/pampers.jpg
labelme/products/pantene.jpg
labelme/utils/__init__.py
labelme/utils/_io.py
labelme/utils/image.py
labelme/utils/qt.py
labelme/utils/shape.py
labelme/widgets/__init__.py
labelme/widgets/canvas.py
labelme/widgets/color_dialog.py
labelme/widgets/escapable_qlist_widget.py
labelme/widgets/label_dialog.py
labelme/widgets/label_dialog_auto.py
labelme/widgets/label_list_widget.py
labelme/widgets/product_view_widget.py
labelme/widgets/tool_bar.py
labelmex.egg-info/PKG-INFO
labelmex.egg-info/SOURCES.txt
labelmex.egg-info/dependency_links.txt
labelmex.egg-info/entry_points.txt
labelmex.egg-info/requires.txt
labelmex.egg-info/top_level.txt