Metadata-Version: 2.1
Name: labelmex
Version: 1.0.3
Summary: Image Polygonal Annotation with Python
Home-page: https://github.com/jjpanda/labelmeX
Author: JJ Pan
Author-email: pjunjie@gmail.com
License: GPLv3
Keywords: Image Annotation,Machine Learning
Platform: UNKNOWN
Classifier: Development Status :: 5 - Production/Stable
Classifier: Intended Audience :: Developers
Classifier: Natural Language :: English
Classifier: Programming Language :: Python
Classifier: Programming Language :: Python :: 2.7
Classifier: Programming Language :: Python :: 3.5
Classifier: Programming Language :: Python :: 3.6
Classifier: Programming Language :: Python :: 3.7
Classifier: Programming Language :: Python :: Implementation :: CPython
Classifier: Programming Language :: Python :: Implementation :: PyPy
